tools_Luis_Schuimer/__init__.py
tools_Luis_Schuimer/tools.py
tools_luis_schuimer-0.1.dist-info/METADATA
tools_luis_schuimer-0.1.dist-info/WHEEL
tools_luis_schuimer-0.1.dist-info/licenses/LICENCE
tools_luis_schuimer-0.1.dist-info/RECORD
