Metadata-Version: 2.1
Name: tools_Luis_Schuimer
Version: 0.1
Summary: A compilation of packages
Author-email: Luis Schuimer <luis.schuimer@outlook.com>
License-File: LICENCE
Classifier: License :: OSI Approved :: MIT License
Classifier: Operating System :: OS Independent
Classifier: Programming Language :: Python :: 3
Requires-Python: >=3.9
